pydiscordhelper/__init__.py
pydiscordhelper/main.py
pydiscordhelper-1.1.2.dist-info/METADATA
pydiscordhelper-1.1.2.dist-info/WHEEL
pydiscordhelper-1.1.2.dist-info/top_level.txt
pydiscordhelper-1.1.2.dist-info/RECORD
